torch_betainc/__init__.py
torch_betainc/_utils.py
torch_betainc/betainc.py
torch_betainc/distributions.py
torch_betainc-0.2.0.dist-info/licenses/LICENSE
torch_betainc-0.2.0.dist-info/METADATA
torch_betainc-0.2.0.dist-info/WHEEL
torch_betainc-0.2.0.dist-info/top_level.txt
torch_betainc-0.2.0.dist-info/RECORD
