Metadata-Version: 2.4
Name: torch-betainc
Version: 0.2.0
Summary: Differentiable incomplete beta function for PyTorch
Author-email: Keisuke Onoue <k.onoue0724@gmail.com>
License: MIT
Project-URL: Homepage, https://github.com/k-onoue/torch-betainc
Project-URL: Repository, https://github.com/k-onoue/torch-betainc
Project-URL: Documentation, https://github.com/k-onoue/torch-betainc#readme
Project-URL: Bug Tracker, https://github.com/k-onoue/torch-betainc/issues
Project-URL: Original Work, https://github.com/arzwa/IncBetaDer
Keywords: pytorch,incomplete-beta,special-functions,differentiable,autograd
Classifier: Development Status :: 3 - Alpha
Classifier: Intended Audience :: Science/Research
Classifier: Intended Audience :: Developers
Classifier: License :: OSI Approved :: MIT License
Classifier: Programming Language :: Python :: 3
Classifier: Programming Language :: Python :: 3.8
Classifier: Programming Language :: Python :: 3.9
Classifier: Programming Language :: Python :: 3.10
Classifier: Programming Language :: Python :: 3.11
Classifier: Programming Language :: Python :: 3.12
Classifier: Topic :: Scientific/Engineering
Classifier: Topic :: Scientific/Engineering :: Mathematics
Classifier: Topic :: Software Development :: Libraries :: Python Modules
Requires-Python: >=3.8
License-File: LICENSE
Requires-Dist: torch>=1.9.0
Provides-Extra: dev
Requires-Dist: pytest>=7.0.0; extra == "dev"
Requires-Dist: pytest-cov>=4.0.0; extra == "dev"
Provides-Extra: examples
Requires-Dist: matplotlib>=3.5.0; extra == "examples"
Requires-Dist: seaborn>=0.12.0; extra == "examples"
Provides-Extra: notebook
Requires-Dist: numpy>=1.21.0; extra == "notebook"
Requires-Dist: scipy>=1.7.0; extra == "notebook"
Requires-Dist: matplotlib>=3.5.0; extra == "notebook"
Requires-Dist: seaborn>=0.12.0; extra == "notebook"
Requires-Dist: jupyter>=1.0.0; extra == "notebook"
Requires-Dist: ipykernel>=6.0.0; extra == "notebook"
Dynamic: license-file
